[{"public_metrics": {"retweet_count": 0, "reply_count": 0, "like_count": 0, "quote_count": 0, "bookmark_count": 0, "impression_count": 41}, "text": "Kami meyakini bahwa dengan melakukan fogging nyamuk DBD secara rutin penyebaran penyakit demam berdarah dapat diatasi dengan baik.\n#8terdepan https://t.co/lxSmSCjVX6", "attachments": {"media_keys": ["3_1689639603324817408"]}, "possibly_sensitive": false, "conversation_id": "1689639611168165888", "edit_controls": {"edits_remaining": 5, "is_edit_eligible": true, "editable_until": "2023-08-10T15:07:29.000Z"}, "entities": {"urls": [{"start": 142, "end": 165, "url": "https://t.co/lxSmSCjVX6", "expanded_url": "https://twitter.com/Untungsuropa/status/1689639611168165888/photo/1", "display_url": "pic.twitter.com/lxSmSCjVX6", "media_key": "3_1689639603324817408"}], "hashtags": [{"start": 131, "end": 141, "tag": "8terdepan"}]}, "created_at": "2023-08-10T14:07:29.000Z", "author_id": "815831168704614400", "reply_settings": "everyone", "lang": "in", "id": "1689639611168165888", "edit_history_tweet_ids": ["1689639611168165888"]}, {"public_metrics": {"retweet_count": 0, "reply_count": 0, "like_count": 0, "quote_count": 0, "bookmark_count": 0, "impression_count": 36}, "text": "Bersama-sama kita bisa memutus rantai penyebaran penyakit demam berdarah mari bergabung dengan pelayanan fogging nyamuk DBD dari PKS Kabupaten Bandung.\n#8terdepan https://t.co/RaIHubwduy", "attachments": {"media_keys": ["3_1689639535700029440"]}, "possibly_sensitive": false, "conversation_id": "1689639543409197056", "edit_controls": {"edits_remaining": 5, "is_edit_eligible": true, "editable_until": "2023-08-10T15:07:13.000Z"}, "entities": {"urls": [{"start": 163, "end": 186, "url": "https://t.co/RaIHubwduy", "expanded_url": "https://twitter.com/Untungsuropa/status/1689639543409197056/photo/1", "display_url": "pic.twitter.com/RaIHubwduy", "media_key": "3_1689639535700029440"}], "hashtags": [{"start": 152, "end": 162, "tag": "8terdepan"}]}, "created_at": "2023-08-10T14:07:13.000Z", "author_id": "815831168704614400", "reply_settings": "everyone", "lang": "in", "id": "1689639543409197056", "edit_history_tweet_ids": ["1689639543409197056"]}, {"public_metrics": {"retweet_count": 0, "reply_count": 0, "like_count": 0, "quote_count": 0, "bookmark_count": 0, "impression_count": 5}, "text": "Kami siap memberikan informasi lebih lanjut tentang pelayanan fogging nyamuk DBD dari PKS Kabupaten Bandung.\n#8terdepan", "possibly_sensitive": false, "conversation_id": "1689639452203995137", "edit_controls": {"edits_remaining": 5, "is_edit_eligible": true, "editable_until": "2023-08-10T15:06:52.000Z"}, "created_at": "2023-08-10T14:06:52.000Z", "author_id": "815831168704614400", "entities": {"hashtags": [{"start": 109, "end": 119, "tag": "8terdepan"}]}, "reply_settings": "everyone", "lang": "in", "id": "1689639452203995137", "edit_history_tweet_ids": ["1689639452203995137"]}, {"public_metrics": {"retweet_count": 0, "reply_count": 0, "like_count": 0, "quote_count": 0, "bookmark_count": 0, "impression_count": 8}, "text": "Kami memberikan jaminan bahwa fogging nyamuk DBD yang kami lakukan aman bagi kesehatan Anda dan keluarga.\n#8terdepan", "possibly_sensitive": false, "conversation_id": "1689639286759735296", "edit_controls": {"edits_remaining": 5, "is_edit_eligible": true, "editable_until": "2023-08-10T15:06:12.000Z"}, "created_at": "2023-08-10T14:06:12.000Z", "author_id": "815831168704614400", "entities": {"hashtags": [{"start": 106, "end": 116, "tag": "8terdepan"}]}, "reply_settings": "everyone", "lang": "in", "id": "1689639286759735296", "edit_history_tweet_ids": ["1689639286759735296"]}, {"public_metrics": {"retweet_count": 0, "reply_count": 0, "like_count": 1, "quote_count": 0, "bookmark_count": 0, "impression_count": 26}, "text": "Jadikan fogging nyamuk DBD dari PKS Kabupaten Bandung sebagai pilihan utama Anda dalam mengatasi masalah nyamuk dan penyakit demam berdarah.\n#8terdepan", "possibly_sensitive": false, "conversation_id": "1689639224973434880", "edit_controls": {"edits_remaining": 5, "is_edit_eligible": true, "editable_until": "2023-08-10T15:05:57.000Z"}, "created_at": "2023-08-10T14:05:57.000Z", "author_id": "815831168704614400", "entities": {"hashtags": [{"start": 141, "end": 151, "tag": "8terdepan"}]}, "reply_settings": "everyone", "lang": "in", "id": "1689639224973434880", "edit_history_tweet_ids": ["1689639224973434880"]}, {"public_metrics": {"retweet_count": 0, "reply_count": 0, "like_count": 1, "quote_count": 0, "bookmark_count": 0, "impression_count": 26}, "text": "Melalui fogging nyamuk DBD kami berharap dapat menjaga kesehatan masyarakat dan mengurangi penyebaran penyakit demam berdarah.\n#8terdepan", "possibly_sensitive": false, "conversation_id": "1689639168438366209", "edit_controls": {"edits_remaining": 5, "is_edit_eligible": true, "editable_until": "2023-08-10T15:05:44.000Z"}, "created_at": "2023-08-10T14:05:44.000Z", "author_id": "815831168704614400", "entities": {"hashtags": [{"start": 127, "end": 137, "tag": "8terdepan"}]}, "reply_settings": "everyone", "lang": "in", "id": "1689639168438366209", "edit_history_tweet_ids": ["1689639168438366209"]}, {"public_metrics": {"retweet_count": 0, "reply_count": 0, "like_count": 0, "quote_count": 0, "bookmark_count": 0, "impression_count": 8}, "text": "Jangan ragu untuk menghubungi pelayanan fogging nyamuk DBD dari PKS Kabupaten Bandung saat Anda membutuhkannya.\n#8terdepan", "possibly_sensitive": false, "conversation_id": "1689639120317140992", "edit_controls": {"edits_remaining": 5, "is_edit_eligible": true, "editable_until": "2023-08-10T15:05:32.000Z"}, "created_at": "2023-08-10T14:05:32.000Z", "author_id": "815831168704614400", "entities": {"hashtags": [{"start": 112, "end": 122, "tag": "8terdepan"}]}, "reply_settings": "everyone", "lang": "in", "id": "1689639120317140992", "edit_history_tweet_ids": ["1689639120317140992"]}, {"public_metrics": {"retweet_count": 0, "reply_count": 0, "like_count": 2, "quote_count": 0, "bookmark_count": 0, "impression_count": 21}, "text": "DPD PKS Kabupaten Bandung berkomitmen untuk memberikan pelayanan fogging nyamuk DBD yang terbaik kepada masyarakat.\n#8terdepan https://t.co/vWGJL6gxah", "attachments": {"media_keys": ["3_1689638898304159744"]}, "possibly_sensitive": false, "conversation_id": "1689638906457890817", "edit_controls": {"edits_remaining": 5, "is_edit_eligible": true, "editable_until": "2023-08-10T15:04:41.000Z"}, "entities": {"urls": [{"start": 127, "end": 150, "url": "https://t.co/vWGJL6gxah", "expanded_url": "https://twitter.com/Untungsuropa/status/1689638906457890817/photo/1", "display_url": "pic.twitter.com/vWGJL6gxah", "media_key": "3_1689638898304159744"}], "hashtags": [{"start": 116, "end": 126, "tag": "8terdepan"}]}, "created_at": "2023-08-10T14:04:41.000Z", "author_id": "815831168704614400", "reply_settings": "everyone", "lang": "in", "id": "1689638906457890817", "edit_history_tweet_ids": ["1689638906457890817"]}, {"public_metrics": {"retweet_count": 0, "reply_count": 0, "like_count": 1, "quote_count": 0, "bookmark_count": 0, "impression_count": 18}, "text": "Selain fogging nyamuk DBD kami juga memberikan edukasi tentang pencegahan demam berdarah kepada masyarakat.\n#8terdepan https://t.co/RHtnzvoIO4", "attachments": {"media_keys": ["3_1689638783858405376"]}, "possibly_sensitive": false, "conversation_id": "1689638790070255616", "edit_controls": {"edits_remaining": 5, "is_edit_eligible": true, "editable_until": "2023-08-10T15:04:14.000Z"}, "entities": {"urls": [{"start": 119, "end": 142, "url": "https://t.co/RHtnzvoIO4", "expanded_url": "https://twitter.com/Untungsuropa/status/1689638790070255616/photo/1", "display_url": "pic.twitter.com/RHtnzvoIO4", "media_key": "3_1689638783858405376"}], "hashtags": [{"start": 108, "end": 118, "tag": "8terdepan"}]}, "created_at": "2023-08-10T14:04:14.000Z", "author_id": "815831168704614400", "reply_settings": "everyone", "lang": "in", "id": "1689638790070255616", "edit_history_tweet_ids": ["1689638790070255616"]}, {"public_metrics": {"retweet_count": 0, "reply_count": 0, "like_count": 0, "quote_count": 0, "bookmark_count": 0, "impression_count": 6}, "text": "Pelayanan fogging nyamuk DBD dari PKS Kabupaten Bandung dilaksanakan secara berkala untuk memastikan kebersihan dan kesehatan masyarakat.\n#8terdepan https://t.co/kuq1HZ3ghR", "attachments": {"media_keys": ["3_1689638677713190915"]}, "possibly_sensitive": false, "conversation_id": "1689638682998063108", "edit_controls": {"edits_remaining": 5, "is_edit_eligible": true, "editable_until": "2023-08-10T15:03:48.000Z"}, "entities": {"urls": [{"start": 149, "end": 172, "url": "https://t.co/kuq1HZ3ghR", "expanded_url": "https://twitter.com/Untungsuropa/status/1689638682998063108/photo/1", "display_url": "pic.twitter.com/kuq1HZ3ghR", "media_key": "3_1689638677713190915"}], "hashtags": [{"start": 138, "end": 148, "tag": "8terdepan"}]}, "created_at": "2023-08-10T14:03:48.000Z", "author_id": "815831168704614400", "reply_settings": "everyone", "lang": "in", "id": "1689638682998063108", "edit_history_tweet_ids": ["1689638682998063108"]}, {"public_metrics": {"retweet_count": 0, "reply_count": 0, "like_count": 0, "quote_count": 0, "bookmark_count": 0, "impression_count": 14}, "text": "Kami menggunakan bahan fogging yang aman dan teruji untuk membasmi nyamuk DBD di lingkungan Anda.\n#8terdepan https://t.co/CrKQaRj0c5", "attachments": {"media_keys": ["3_1689638413061009411"]}, "possibly_sensitive": false, "conversation_id": "1689638418605801473", "edit_controls": {"edits_remaining": 5, "is_edit_eligible": true, "editable_until": "2023-08-10T15:02:45.000Z"}, "entities": {"urls": [{"start": 109, "end": 132, "url": "https://t.co/CrKQaRj0c5", "expanded_url": "https://twitter.com/Untungsuropa/status/1689638418605801473/photo/1", "display_url": "pic.twitter.com/CrKQaRj0c5", "media_key": "3_1689638413061009411"}], "hashtags": [{"start": 98, "end": 108, "tag": "8terdepan"}]}, "created_at": "2023-08-10T14:02:45.000Z", "author_id": "815831168704614400", "reply_settings": "everyone", "lang": "in", "id": "1689638418605801473", "edit_history_tweet_ids": ["1689638418605801473"]}, {"public_metrics": {"retweet_count": 0, "reply_count": 0, "like_count": 0, "quote_count": 0, "bookmark_count": 0, "impression_count": 9}, "text": "Pelayanan fogging nyamuk DBD dari PKS Kabupaten Bandung dapat dihubungi melalui nomor telepon yang telah disediakan.\n#8terdepan https://t.co/AFHONSvI7e", "attachments": {"media_keys": ["3_1689638308568281088"]}, "possibly_sensitive": false, "conversation_id": "1689638315153403905", "edit_controls": {"edits_remaining": 5, "is_edit_eligible": true, "editable_until": "2023-08-10T15:02:20.000Z"}, "entities": {"urls": [{"start": 128, "end": 151, "url": "https://t.co/AFHONSvI7e", "expanded_url": "https://twitter.com/Untungsuropa/status/1689638315153403905/photo/1", "display_url": "pic.twitter.com/AFHONSvI7e", "media_key": "3_1689638308568281088"}], "hashtags": [{"start": 117, "end": 127, "tag": "8terdepan"}]}, "created_at": "2023-08-10T14:02:20.000Z", "author_id": "815831168704614400", "context_annotations": [{"domain": {"id": "46", "name": "Business Taxonomy", "description": "Categories within Brand Verticals that narrow down the scope of Brands"}, "entity": {"id": "1557696940178935808", "name": "Gaming Business", "description": "Brands, companies, advertisers and every non-person handle with the profit intent related to offline and online games such as gaming consoles, tabletop games, video game publishers"}}], "reply_settings": "everyone", "lang": "in", "id": "1689638315153403905", "edit_history_tweet_ids": ["1689638315153403905"]}, {"public_metrics": {"retweet_count": 0, "reply_count": 0, "like_count": 0, "quote_count": 0, "bookmark_count": 0, "impression_count": 11}, "text": "Tim fogging PKS Kabupaten Bandung siap datang ke rumah Anda untuk melakukan fogging nyamuk DBD secara gratis.\n#8terdepan", "possibly_sensitive": false, "conversation_id": "1689638225030369280", "edit_controls": {"edits_remaining": 5, "is_edit_eligible": true, "editable_until": "2023-08-10T15:01:59.000Z"}, "created_at": "2023-08-10T14:01:59.000Z", "author_id": "815831168704614400", "entities": {"hashtags": [{"start": 110, "end": 120, "tag": "8terdepan"}]}, "reply_settings": "everyone", "lang": "in", "id": "1689638225030369280", "edit_history_tweet_ids": ["1689638225030369280"]}, {"public_metrics": {"retweet_count": 0, "reply_count": 0, "like_count": 0, "quote_count": 0, "bookmark_count": 0, "impression_count": 37}, "text": "Kami melakukan fogging nyamuk DBD sebagai upaya dalam mengendalikan penyebaran penyakit demam berdarah di Kabupaten Bandung.\n#8terdepan https://t.co/aV4sgpaCEj", "attachments": {"media_keys": ["3_1689638158475141120"]}, "possibly_sensitive": false, "conversation_id": "1689638164732981248", "edit_controls": {"edits_remaining": 5, "is_edit_eligible": true, "editable_until": "2023-08-10T15:01:45.000Z"}, "entities": {"urls": [{"start": 136, "end": 159, "url": "https://t.co/aV4sgpaCEj", "expanded_url": "https://twitter.com/Untungsuropa/status/1689638164732981248/photo/1", "display_url": "pic.twitter.com/aV4sgpaCEj", "media_key": "3_1689638158475141120"}], "hashtags": [{"start": 125, "end": 135, "tag": "8terdepan"}]}, "created_at": "2023-08-10T14:01:45.000Z", "author_id": "815831168704614400", "context_annotations": [{"domain": {"id": "46", "name": "Business Taxonomy", "description": "Categories within Brand Verticals that narrow down the scope of Brands"}, "entity": {"id": "1557696940178935808", "name": "Gaming Business", "description": "Brands, companies, advertisers and every non-person handle with the profit intent related to offline and online games such as gaming consoles, tabletop games, video game publishers"}}], "reply_settings": "everyone", "lang": "in", "id": "1689638164732981248", "edit_history_tweet_ids": ["1689638164732981248"]}, {"public_metrics": {"retweet_count": 0, "reply_count": 0, "like_count": 0, "quote_count": 0, "bookmark_count": 0, "impression_count": 4}, "text": "DPD PKS Kabupaten Bandung senantiasa siap memberikan pelayanan fogging nyamuk DBD kepada masyarakat.\n#8terdepan https://t.co/Hw3ArKxDvx", "attachments": {"media_keys": ["3_1689638089378181122"]}, "possibly_sensitive": false, "conversation_id": "1689638096361684997", "edit_controls": {"edits_remaining": 5, "is_edit_eligible": true, "editable_until": "2023-08-10T15:01:28.000Z"}, "entities": {"urls": [{"start": 112, "end": 135, "url": "https://t.co/Hw3ArKxDvx", "expanded_url": "https://twitter.com/Untungsuropa/status/1689638096361684997/photo/1", "display_url": "pic.twitter.com/Hw3ArKxDvx", "media_key": "3_1689638089378181122"}], "hashtags": [{"start": 101, "end": 111, "tag": "8terdepan"}]}, "created_at": "2023-08-10T14:01:28.000Z", "author_id": "815831168704614400", "reply_settings": "everyone", "lang": "in", "id": "1689638096361684997", "edit_history_tweet_ids": ["1689638096361684997"]}, {"public_metrics": {"retweet_count": 0, "reply_count": 0, "like_count": 2, "quote_count": 0, "bookmark_count": 0, "impression_count": 18}, "text": "Lagi Main Asap Dulu. \nAmpe gak keliatan Si Abang gegara ketutupan asap. \nIni lagi fogging, ngusir nyamuk DBD. \nProgram rutin ni. Keren kan? \n#8terdepan https://t.co/2AJwMC2RA6", "attachments": {"media_keys": ["3_1689634468280373248"]}, "possibly_sensitive": false, "conversation_id": "1689634473783214082", "edit_controls": {"edits_remaining": 5, "is_edit_eligible": true, "editable_until": "2023-08-10T14:47:05.000Z"}, "entities": {"urls": [{"start": 152, "end": 175, "url": "https://t.co/2AJwMC2RA6", "expanded_url": "https://twitter.com/umminejahid/status/1689634473783214082/photo/1", "display_url": "pic.twitter.com/2AJwMC2RA6", "media_key": "3_1689634468280373248"}], "hashtags": [{"start": 141, "end": 151, "tag": "8terdepan"}]}, "created_at": "2023-08-10T13:47:05.000Z", "author_id": "1196085449866936321", "context_annotations": [{"domain": {"id": "46", "name": "Business Taxonomy", "description": "Categories within Brand Verticals that narrow down the scope of Brands"}, "entity": {"id": "1557696940178935808", "name": "Gaming Business", "description": "Brands, companies, advertisers and every non-person handle with the profit intent related to offline and online games such as gaming consoles, tabletop games, video game publishers"}}], "reply_settings": "everyone", "lang": "in", "id": "1689634473783214082", "edit_history_tweet_ids": ["1689634473783214082"]}, {"public_metrics": {"retweet_count": 0, "reply_count": 1, "like_count": 0, "quote_count": 0, "bookmark_count": 0, "impression_count": 273}, "text": "apalagi gigitan nyamuk itu efeknya bisa sampe DBD malaria huhu ngeri", "possibly_sensitive": false, "conversation_id": "1689629029329149952", "edit_controls": {"edits_remaining": 5, "is_edit_eligible": false, "editable_until": "2023-08-10T14:25:28.000Z"}, "created_at": "2023-08-10T13:25:28.000Z", "author_id": "1371650588", "reply_settings": "everyone", "lang": "in", "id": "1689629037407436800", "edit_history_tweet_ids": ["1689629037407436800"], "referenced_tweets": [{"type": "replied_to", "id": "1689629029329149952"}], "in_reply_to_user_id": "1371650588"}, {"public_metrics": {"retweet_count": 0, "reply_count": 1, "like_count": 0, "quote_count": 0, "bookmark_count": 0, "impression_count": 75}, "text": "@phobiatelor Musim kemarau kak banyak nyamuk, tiati dbd", "possibly_sensitive": false, "conversation_id": "1689619234199052288", "edit_controls": {"edits_remaining": 5, "is_edit_eligible": false, "editable_until": "2023-08-10T13:56:15.000Z"}, "created_at": "2023-08-10T12:56:15.000Z", "author_id": "1010152412684828673", "reply_settings": "everyone", "lang": "in", "id": "1689621681248342016", "edit_history_tweet_ids": ["1689621681248342016"], "entities": {"mentions": [{"start": 0, "end": 12, "username": "phobiatelor", "id": "754667552"}]}, "referenced_tweets": [{"type": "replied_to", "id": "1689621553640857600"}], "in_reply_to_user_id": "754667552"}, {"public_metrics": {"retweet_count": 0, "reply_count": 0, "like_count": 0, "quote_count": 0, "bookmark_count": 0, "impression_count": 50}, "text": "otw dbd digigit nyamuk", "possibly_sensitive": false, "conversation_id": "1689524671652470784", "edit_controls": {"edits_remaining": 5, "is_edit_eligible": true, "editable_until": "2023-08-10T07:30:46.000Z"}, "created_at": "2023-08-10T06:30:46.000Z", "author_id": "1516807757566939140", "reply_settings": "everyone", "lang": "in", "id": "1689524671652470784", "edit_history_tweet_ids": ["1689524671652470784"]}, {"public_metrics": {"retweet_count": 0, "reply_count": 0, "like_count": 0, "quote_count": 0, "bookmark_count": 0, "impression_count": 216}, "text": "@incitu Astoge lanjutannya knp ga kepost td\n\nEx: uda usaha hidup sehat... Mendadak digigit nyamuk pas maen k taman... Badan pas capek... Trus jdilah DBD... Rawat inap bbrpa hari eh habisnya uda 5 jutaan... Ga sanggop aku kalo gada BPJS mah", "possibly_sensitive": false, "conversation_id": "1689443591977041920", "edit_controls": {"edits_remaining": 5, "is_edit_eligible": false, "editable_until": "2023-08-10T06:51:05.000Z"}, "created_at": "2023-08-10T05:51:05.000Z", "author_id": "101680720", "context_annotations": [{"domain": {"id": "88", "name": "Political Body", "description": "A section of a government, like The Supreme Court"}, "entity": {"id": "1209133540245307393", "name": " The Indonesian National Health Insurance"}}], "reply_settings": "everyone", "lang": "in", "id": "1689514685215948801", "edit_history_tweet_ids": ["1689514685215948801"], "entities": {"mentions": [{"start": 0, "end": 7, "username": "incitu", "id": "1370325994486198272"}]}, "referenced_tweets": [{"type": "replied_to", "id": "1689476840283627520"}], "in_reply_to_user_id": "101680720"}, {"public_metrics": {"retweet_count": 0, "reply_count": 0, "like_count": 1, "quote_count": 0, "bookmark_count": 0, "impression_count": 67}, "text": "Insektisida Seruni 100 EC 500 ml Obat Fogging Nyamuk DBD Sipermetrin seharga Rp69.000. \nhttps://t.co/K6oXJFUNQX\n\n#Seruni100EC #ObatFogging #ObatFoggingNyamuk #BasmiNyamuk #PengendalianNyamuk https://t.co/nfqyu0ayjb", "attachments": {"media_keys": ["3_1689507953462894592"]}, "possibly_sensitive": false, "conversation_id": "1689508265980485632", "edit_controls": {"edits_remaining": 5, "is_edit_eligible": true, "editable_until": "2023-08-10T06:25:34.000Z"}, "entities": {"urls": [{"start": 88, "end": 111, "url": "https://t.co/K6oXJFUNQX", "expanded_url": "https://shopee.co.id/taktumbas/8363330210", "display_url": "shopee.co.id/taktumbas/8363\u2026", "status": 404, "unwound_url": "https://shopee.co.id/product/135976886/8363330210"}, {"start": 191, "end": 214, "url": "https://t.co/nfqyu0ayjb", "expanded_url": "https://twitter.com/TumbasTak18824/status/1689508265980485632/photo/1", "display_url": "pic.twitter.com/nfqyu0ayjb", "media_key": "3_1689507953462894592"}], "hashtags": [{"start": 113, "end": 125, "tag": "Seruni100EC"}, {"start": 126, "end": 138, "tag": "ObatFogging"}, {"start": 139, "end": 157, "tag": "ObatFoggingNyamuk"}, {"start": 158, "end": 170, "tag": "BasmiNyamuk"}, {"start": 171, "end": 190, "tag": "PengendalianNyamuk"}]}, "created_at": "2023-08-10T05:25:34.000Z", "author_id": "1671705528463138816", "reply_settings": "everyone", "lang": "in", "id": "1689508265980485632", "edit_history_tweet_ids": ["1689508265980485632"]}, {"public_metrics": {"retweet_count": 0, "reply_count": 0, "like_count": 0, "quote_count": 0, "bookmark_count": 0, "impression_count": 13}, "text": "Cek Hit GoodKnight Non Stop Refill Fresh 45 Hari x2- Refill Obat Nyamuk Elektrik - Bunuh Nyamuk Penyebab Demam Berdarah (DBD) dengan harga Rp29.200. Dapatkan di Shopee sekarang! https://t.co/L7eYJVsk1V https://t.co/kCpwEhqoTG", "attachments": {"media_keys": ["3_1689431618010873856"]}, "possibly_sensitive": false, "conversation_id": "1689431712386994176", "edit_controls": {"edits_remaining": 5, "is_edit_eligible": true, "editable_until": "2023-08-10T01:21:23.000Z"}, "entities": {"urls": [{"start": 178, "end": 201, "url": "https://t.co/L7eYJVsk1V", "expanded_url": "https://shope.ee/B0h1n7OwS?share_channel_code=7", "display_url": "shope.ee/B0h1n7OwS?shar\u2026", "status": 404, "unwound_url": "https://shopee.co.id/product/73266191/20738929769?utm_campaign=-&utm_content=----&utm_medium=affiliates&utm_source=an_11330150287&utm_term=9pa36y3vew1i"}, {"start": 202, "end": 225, "url": "https://t.co/kCpwEhqoTG", "expanded_url": "https://twitter.com/ZiaPutriAyu/status/1689431712386994176/photo/1", "display_url": "pic.twitter.com/kCpwEhqoTG", "media_key": "3_1689431618010873856"}]}, "created_at": "2023-08-10T00:21:23.000Z", "author_id": "1643729144344358912", "reply_settings": "everyone", "lang": "in", "id": "1689431712386994176", "edit_history_tweet_ids": ["1689431712386994176"]}, {"public_metrics": {"retweet_count": 0, "reply_count": 0, "like_count": 0, "quote_count": 0, "bookmark_count": 0, "impression_count": 8}, "text": "\"Lawan DBD dengan Aksi, Bukan Hanya Harapan! \ud83c\udf3f\ud83e\udd9f Berikut adalah beberapa tips efektif untuk mencegah Demam Berdarah Dengue (DBD): Kenali jentik nyamuk, Buang tempat berair, Pakai baju tertutup, Gunakan lotion anti nyamuk, dan Rutin cek ke dokter. https://t.co/DZWx4Hmyuc", "attachments": {"media_keys": ["3_1689323032836448258"]}, "possibly_sensitive": false, "conversation_id": "1689323211992035328", "edit_controls": {"edits_remaining": 5, "is_edit_eligible": true, "editable_until": "2023-08-09T18:10:14.000Z"}, "entities": {"urls": [{"start": 246, "end": 269, "url": "https://t.co/DZWx4Hmyuc", "expanded_url": "https://twitter.com/UPTDpuskesdago/status/1689323211992035328/photo/1", "display_url": "pic.twitter.com/DZWx4Hmyuc", "media_key": "3_1689323032836448258"}]}, "created_at": "2023-08-09T17:10:14.000Z", "author_id": "1688431773074731009", "reply_settings": "everyone", "lang": "in", "id": "1689323211992035328", "edit_history_tweet_ids": ["1689323211992035328"]}, {"public_metrics": {"retweet_count": 0, "reply_count": 0, "like_count": 0, "quote_count": 0, "bookmark_count": 0, "impression_count": 50}, "text": "Cek Hit Good Knight Xpress Refill Apple 45 Hari x2- Refill Obat Nyamuk Elektrik - Bunuh Nyamuk Penyebab Demam Berdarah (DBD) dengan harga Rp25.900. Dapatkan di Shopee sekarang! https://t.co/Mk3Ed0k4CM https://t.co/CAVmO7JDTH", "attachments": {"media_keys": ["3_1689277354835656704"]}, "possibly_sensitive": false, "conversation_id": "1689277358627274752", "edit_controls": {"edits_remaining": 5, "is_edit_eligible": true, "editable_until": "2023-08-09T15:08:02.000Z"}, "entities": {"urls": [{"start": 177, "end": 200, "url": "https://t.co/Mk3Ed0k4CM", "expanded_url": "https://shope.ee/8zc4rvlkvX?share_channel_code=7", "display_url": "shope.ee/8zc4rvlkvX?sha\u2026", "status": 404, "unwound_url": "https://shopee.co.id/product/73266191/10492029125?utm_campaign=-&utm_content=----&utm_medium=affiliates&utm_source=an_11389170351&utm_term=9p7ir7pd31yh"}, {"start": 201, "end": 224, "url": "https://t.co/CAVmO7JDTH", "expanded_url": "https://twitter.com/imasidoarjo/status/1689277358627274752/photo/1", "display_url": "pic.twitter.com/CAVmO7JDTH", "media_key": "3_1689277354835656704"}]}, "created_at": "2023-08-09T14:08:02.000Z", "author_id": "1618937419595927554", "reply_settings": "everyone", "lang": "in", "id": "1689277358627274752", "edit_history_tweet_ids": ["1689277358627274752"]}, {"public_metrics": {"retweet_count": 0, "reply_count": 3, "like_count": 15, "quote_count": 0, "bookmark_count": 0, "impression_count": 626}, "text": "Mereka membuat sistem fooging nyamuk n asap2 penyanyi dangdut n nyamuk si BG mana bs di kasi konser dangdut n ada2 aja mrk itu ya. biarkan kepintaran saja lah n memeng Atut sm kepintaran n pasien DBD trs mningkat dsni https://t.co/9okw99UHYM", "attachments": {"media_keys": ["7_1689206042675277824"]}, "possibly_sensitive": false, "conversation_id": "1689206101517250560", "edit_controls": {"edits_remaining": 5, "is_edit_eligible": true, "editable_until": "2023-08-09T10:24:53.000Z"}, "entities": {"urls": [{"start": 218, "end": 241, "url": "https://t.co/9okw99UHYM", "expanded_url": "https://twitter.com/DambaanA/status/1689206101517250560/video/1", "display_url": "pic.twitter.com/9okw99UHYM", "media_key": "7_1689206042675277824"}]}, "created_at": "2023-08-09T09:24:53.000Z", "author_id": "1603570929635692545", "context_annotations": [{"domain": {"id": "46", "name": "Business Taxonomy", "description": "Categories within Brand Verticals that narrow down the scope of Brands"}, "entity": {"id": "1557696802391859201", "name": "Entertainment & Leisure Business", "description": "Brands, companies, advertisers and every non-person handle with the profit intent related to movies, music, television, franchises, venues, theme parks, toys, tourism, hotels"}}, {"domain": {"id": "55", "name": "Music Genre", "description": "A category for a musical style, like Pop, Rock, or Rap"}, "entity": {"id": "1332247934113521666", "name": "Dangdut music"}}, {"domain": {"id": "131", "name": "Unified Twitter Taxonomy", "description": "A taxonomy of user interests. "}, "entity": {"id": "847524658970636288", "name": "Music", "description": "Music and radio"}}, {"domain": {"id": "131", "name": "Unified Twitter Taxonomy", "description": "A taxonomy of user interests. "}, "entity": {"id": "1332247934113521666", "name": "Dangdut music"}}, {"domain": {"id": "131", "name": "Unified Twitter Taxonomy", "description": "A taxonomy of user interests. "}, "entity": {"id": "1526859422919643137", "name": "Indonesian music"}}], "reply_settings": "everyone", "lang": "in", "id": "1689206101517250560", "edit_history_tweet_ids": ["1689206101517250560"]}, {"public_metrics": {"retweet_count": 0, "reply_count": 0, "like_count": 0, "quote_count": 0, "bookmark_count": 0, "impression_count": 60}, "text": "@AndyHuskyyy Skena apaan digigitin nyamuk pulang2 dbd iyak mas\ud83d\ude14\ud83d\ude14\ud83d\ude14\ud83d\ude14", "possibly_sensitive": false, "conversation_id": "1689138903457071105", "edit_controls": {"edits_remaining": 5, "is_edit_eligible": false, "editable_until": "2023-08-09T06:02:46.000Z"}, "created_at": "2023-08-09T05:02:46.000Z", "author_id": "1072796579268984832", "reply_settings": "everyone", "lang": "in", "id": "1689140140059635712", "edit_history_tweet_ids": ["1689140140059635712"], "entities": {"mentions": [{"start": 0, "end": 12, "username": "AndyHuskyyy", "id": "1134854001827041281"}]}, "referenced_tweets": [{"type": "replied_to", "id": "1689140030458249216"}], "in_reply_to_user_id": "1134854001827041281"}, {"public_metrics": {"retweet_count": 0, "reply_count": 0, "like_count": 0, "quote_count": 0, "bookmark_count": 0, "impression_count": 104}, "text": "Lagi musim DBD kayanya, di komplekku lagi rutin fogging karena emang banyak bgt nyamuk. https://t.co/sd7pqJreCx", "possibly_sensitive": false, "conversation_id": "1689076321065017344", "edit_controls": {"edits_remaining": 5, "is_edit_eligible": true, "editable_until": "2023-08-09T01:49:11.000Z"}, "entities": {"urls": [{"start": 88, "end": 111, "url": "https://t.co/sd7pqJreCx", "expanded_url": "https://twitter.com/hermawan_devina/status/1688733212435218433", "display_url": "twitter.com/hermawan_devin\u2026"}]}, "created_at": "2023-08-09T00:49:11.000Z", "author_id": "1361150598607904768", "reply_settings": "everyone", "lang": "in", "id": "1689076321065017344", "edit_history_tweet_ids": ["1689076321065017344"], "referenced_tweets": [{"type": "quoted", "id": "1688733212435218433"}]}, {"public_metrics": {"retweet_count": 1, "reply_count": 1, "like_count": 1, "quote_count": 0, "bookmark_count": 0, "impression_count": 88}, "text": "\ud83d\udce2 HMJ KESEHATAN MASYARAKAT 2022/2023 PROUDLY PRESENT \ud83d\udce2\n\n\u2728Seminar Kesehatan\u2728\n\nTema : \"KENDALIKAN DBD DENGAN NYAMUK BER-WOLBACHIA\"\n\n\u25ab\ufe0fTERBUKA UNTUK UMUM \u25ab\ufe0f\n\n\u2757Save the Date\u2757\n\ud83d\uddd3\ufe0f : Sabtu, 12 Agustus 2023\n\ud83d\udd58 : 09.00 - Selesai (WIB)\n\ud83d\udccd : Via Zoom Meeting https://t.co/Ck5Jd1k1hQ", "attachments": {"media_keys": ["3_1689073587809099776"]}, "possibly_sensitive": false, "conversation_id": "1689073593886662656", "edit_controls": {"edits_remaining": 5, "is_edit_eligible": false, "editable_until": "2023-08-09T01:38:20.000Z"}, "entities": {"urls": [{"start": 246, "end": 269, "url": "https://t.co/Ck5Jd1k1hQ", "expanded_url": "https://twitter.com/FSKESMASUEU/status/1689073593886662656/photo/1", "display_url": "pic.twitter.com/Ck5Jd1k1hQ", "media_key": "3_1689073587809099776"}]}, "created_at": "2023-08-09T00:38:20.000Z", "author_id": "387489054", "context_annotations": [{"domain": {"id": "45", "name": "Brand Vertical", "description": "Top level entities that describe a Brands industry"}, "entity": {"id": "781974597226799105", "name": "B2B"}}, {"domain": {"id": "30", "name": "Entities [Entity Service]", "description": "Entity Service top level domain, every item that is in Entity Service should be in this domain"}, "entity": {"id": "781974597172203520", "name": "Services - B2B"}}, {"domain": {"id": "47", "name": "Brand", "description": "Brands and Companies"}, "entity": {"id": "10040912121", "name": "Zoom"}}], "reply_settings": "everyone", "lang": "in", "id": "1689073593886662656", "edit_history_tweet_ids": ["1689073593886662656"]}, {"public_metrics": {"retweet_count": 0, "reply_count": 1, "like_count": 0, "quote_count": 0, "bookmark_count": 0, "impression_count": 69}, "text": "@UnguLiam yang masih digenggam oleh Liam.\n\n\u201cYuk, deh. Udah malem juga.\u201d Ranara berusaha mengeluarkan senyuman lebarnya agar ia dapat mengakhiri kecanggung di antara mereka berdua. \u201cBanyak nyamuk, njir. Takut DBD gue. Udah tau darah gue manis.\u201d Racau Ranara untuk mencairkan suasana.", "possibly_sensitive": false, "conversation_id": "1688187372046094337", "edit_controls": {"edits_remaining": 5, "is_edit_eligible": false, "editable_until": "2023-08-08T17:28:27.000Z"}, "created_at": "2023-08-08T16:28:27.000Z", "author_id": "867367079929757701", "reply_settings": "everyone", "lang": "in", "id": "1688950309648056320", "edit_history_tweet_ids": ["1688950309648056320"], "entities": {"mentions": [{"start": 0, "end": 9, "username": "UnguLiam", "id": "840405113432768513"}]}, "referenced_tweets": [{"type": "replied_to", "id": "1688950239045324800"}], "in_reply_to_user_id": "867367079929757701"}, {"public_metrics": {"retweet_count": 0, "reply_count": 1, "like_count": 0, "quote_count": 0, "bookmark_count": 0, "impression_count": 397}, "text": "@vivivi31 @hermawan_devina Tapi kan DBD inangnya nyamuk. Kalau rumahnya jauhan sih biasanya nyamuknya ga nyampe ya", "possibly_sensitive": false, "conversation_id": "1688733212435218433", "edit_controls": {"edits_remaining": 5, "is_edit_eligible": false, "editable_until": "2023-08-08T16:19:24.000Z"}, "created_at": "2023-08-08T15:19:24.000Z", "author_id": "95381610", "context_annotations": [{"domain": {"id": "10", "name": "Person", "description": "Named people in the world like Nelson Mandela"}, "entity": {"id": "1394640086063489029", "name": "Devina Hermawan"}}, {"domain": {"id": "131", "name": "Unified Twitter Taxonomy", "description": "A taxonomy of user interests. "}, "entity": {"id": "1394640086063489029", "name": "Devina Hermawan"}}], "reply_settings": "everyone", "lang": "in", "id": "1688932931321159680", "edit_history_tweet_ids": ["1688932931321159680"], "entities": {"mentions": [{"start": 0, "end": 9, "username": "vivivi31", "id": "1351368040525430784"}, {"start": 10, "end": 26, "username": "hermawan_devina", "id": "1104893764236009472"}]}, "referenced_tweets": [{"type": "replied_to", "id": "1688739399369187328"}], "in_reply_to_user_id": "1351368040525430784"}, {"public_metrics": {"retweet_count": 0, "reply_count": 0, "like_count": 0, "quote_count": 0, "bookmark_count": 0, "impression_count": 16}, "text": "@rockbeatblues Ah maap td nangkep ny sy cm skedar nyamuk sebarin, bkn manusia -&gt; nyamuk -&gt; manusia\n(sy awalny twny cm skedar nyamuk -&gt; manusia)\nDBD ujung2ny emg mslh membasmi nyamuk", "possibly_sensitive": false, "conversation_id": "1688756533864361985", "edit_controls": {"edits_remaining": 5, "is_edit_eligible": false, "editable_until": "2023-08-08T05:09:39.000Z"}, "created_at": "2023-08-08T04:09:39.000Z", "author_id": "74156265", "reply_settings": "everyone", "lang": "in", "id": "1688764383772721152", "edit_history_tweet_ids": ["1688764383772721152"], "entities": {"mentions": [{"start": 0, "end": 14, "username": "rockbeatblues", "id": "1262248874955042816"}]}, "referenced_tweets": [{"type": "replied_to", "id": "1688762235005591552"}], "in_reply_to_user_id": "1262248874955042816"}, {"public_metrics": {"retweet_count": 0, "reply_count": 1, "like_count": 0, "quote_count": 0, "bookmark_count": 0, "impression_count": 36}, "text": "@rockbeatblues Pas ade ku DBD pas di sini dsuru pake anti nyamuk jg biar kl ada nyamuk yg gigit dy ga nularin virus k org lain\nGa bs nular manusia k manusia langsung tp tmpkny bs kl ad perantara nyamuk? tbh blm cek lg n baru denger jg pas ade sakit wkt itu", "possibly_sensitive": false, "conversation_id": "1688756533864361985", "edit_controls": {"edits_remaining": 5, "is_edit_eligible": false, "editable_until": "2023-08-08T04:47:27.000Z"}, "created_at": "2023-08-08T03:47:27.000Z", "author_id": "74156265", "reply_settings": "everyone", "lang": "in", "id": "1688758795001004032", "edit_history_tweet_ids": ["1688758795001004032"], "entities": {"mentions": [{"start": 0, "end": 14, "username": "rockbeatblues", "id": "1262248874955042816"}]}, "referenced_tweets": [{"type": "replied_to", "id": "1688756533864361985"}], "in_reply_to_user_id": "1262248874955042816"}, {"public_metrics": {"retweet_count": 0, "reply_count": 0, "like_count": 0, "quote_count": 0, "bookmark_count": 0, "impression_count": 31}, "text": "Jangan biarkan nyamuk menjadi ancaman! Kenali jenis-jenis nyamuk penyebab penyakit DBD dan basmi mereka segera. Faraya Pest siap membantu menghentikan penyebaran penyakit dengan keahlian dalam membasmi hama. Lindungi kesehatan keluarga dan lingkungan sekitar. https://t.co/P5fZ1Ll8vW", "attachments": {"media_keys": ["7_1688747686202363904"]}, "possibly_sensitive": false, "conversation_id": "1688747907649064960", "edit_controls": {"edits_remaining": 5, "is_edit_eligible": true, "editable_until": "2023-08-08T04:04:11.000Z"}, "entities": {"urls": [{"start": 260, "end": 283, "url": "https://t.co/P5fZ1Ll8vW", "expanded_url": "https://twitter.com/FarayaPest/status/1688747907649064960/video/1", "display_url": "pic.twitter.com/P5fZ1Ll8vW", "media_key": "7_1688747686202363904"}]}, "created_at": "2023-08-08T03:04:11.000Z", "author_id": "872656235530600448", "reply_settings": "everyone", "lang": "in", "id": "1688747907649064960", "edit_history_tweet_ids": ["1688747907649064960"]}, {"public_metrics": {"retweet_count": 0, "reply_count": 0, "like_count": 0, "quote_count": 0, "bookmark_count": 0, "impression_count": 60}, "text": "@Hobah @sbyfess @tahilalats Lo pada mikirin nyamuk yg mati atau km yg mati kena DBD?!!!!", "possibly_sensitive": false, "conversation_id": "1688197250932170752", "edit_controls": {"edits_remaining": 5, "is_edit_eligible": false, "editable_until": "2023-08-07T15:30:30.000Z"}, "created_at": "2023-08-07T14:30:30.000Z", "author_id": "1425304336133869572", "reply_settings": "everyone", "lang": "in", "id": "1688558238294495232", "edit_history_tweet_ids": ["1688558238294495232"], "entities": {"mentions": [{"start": 0, "end": 6, "username": "Hobah", "id": "98329689"}, {"start": 7, "end": 15, "username": "sbyfess", "id": "1152437175587241985"}, {"start": 16, "end": 27, "username": "tahilalats", "id": "823404426"}]}, "referenced_tweets": [{"type": "replied_to", "id": "1688425714742423552"}], "in_reply_to_user_id": "98329689"}, {"public_metrics": {"retweet_count": 0, "reply_count": 1, "like_count": 0, "quote_count": 0, "bookmark_count": 0, "impression_count": 10}, "text": "@tinkerrbeellee Aiih sehat\u00b2 yoo. Jentik nyamuk di penampungan air punya potensi DBD", "possibly_sensitive": false, "conversation_id": "1688517547258478593", "edit_controls": {"edits_remaining": 5, "is_edit_eligible": false, "editable_until": "2023-08-07T14:30:40.000Z"}, "created_at": "2023-08-07T13:30:40.000Z", "author_id": "1656602911366066176", "reply_settings": "everyone", "lang": "in", "id": "1688543179132522496", "edit_history_tweet_ids": ["1688543179132522496"], "entities": {"mentions": [{"start": 0, "end": 15, "username": "tinkerrbeellee", "id": "761766021510209536"}]}, "referenced_tweets": [{"type": "replied_to", "id": "1688542681272844288"}], "in_reply_to_user_id": "761766021510209536"}, {"public_metrics": {"retweet_count": 0, "reply_count": 0, "like_count": 0, "quote_count": 0, "bookmark_count": 0, "impression_count": 62}, "text": "Memang hidup harus YOLO saat tahu liver kena akibat dbd. Fck u nyamuk, kau buat hidupku makin suram \ud83d\udd4a\ufe0f", "possibly_sensitive": false, "conversation_id": "1688515960683237377", "edit_controls": {"edits_remaining": 5, "is_edit_eligible": true, "editable_until": "2023-08-07T12:42:30.000Z"}, "created_at": "2023-08-07T11:42:30.000Z", "author_id": "977780016359460864", "reply_settings": "everyone", "lang": "in", "id": "1688515960683237377", "edit_history_tweet_ids": ["1688515960683237377"]}, {"public_metrics": {"retweet_count": 0, "reply_count": 3, "like_count": 14, "quote_count": 0, "bookmark_count": 0, "impression_count": 641}, "text": "Kami barusan kedatangan rombongan pak RT n mereka bilang sdh ada yg kena DBD sktr 30 orang  n kami sarankan bawang merah n ini bukan smbrang nyamuk n ini nyamuk si BG", "possibly_sensitive": false, "conversation_id": "1688457042883973121", "edit_controls": {"edits_remaining": 5, "is_edit_eligible": true, "editable_until": "2023-08-07T08:48:23.000Z"}, "created_at": "2023-08-07T07:48:23.000Z", "author_id": "1603570929635692545", "reply_settings": "everyone", "lang": "in", "id": "1688457042883973121", "edit_history_tweet_ids": ["1688457042883973121"]}, {"public_metrics": {"retweet_count": 0, "reply_count": 0, "like_count": 7, "quote_count": 0, "bookmark_count": 0, "impression_count": 116}, "text": "Di cuaca ekstrim yg panas ternyata bisa bikin nyamuk DBD makin ganas loh Keluarga Cosmos !! Nah Cosmos punya solusinya ni.. Yuk saksikan Live Unboxing Kipas Angin Cosmos 16 SO 33 ONY tanggal 7 Agustus 2023 pukul 15.00 WIB besok ya. \n\n#BanggaCosmos #LiveUnboxing #KipasAngin https://t.co/rkliytfy0C", "attachments": {"media_keys": ["3_1688431066791710720"]}, "possibly_sensitive": false, "conversation_id": "1688431069400563712", "edit_controls": {"edits_remaining": 5, "is_edit_eligible": true, "editable_until": "2023-08-07T07:05:11.000Z"}, "entities": {"urls": [{"start": 274, "end": 297, "url": "https://t.co/rkliytfy0C", "expanded_url": "https://twitter.com/cosmosonline/status/1688431069400563712/photo/1", "display_url": "pic.twitter.com/rkliytfy0C", "media_key": "3_1688431066791710720"}], "hashtags": [{"start": 234, "end": 247, "tag": "BanggaCosmos"}, {"start": 248, "end": 261, "tag": "LiveUnboxing"}, {"start": 262, "end": 273, "tag": "KipasAngin"}]}, "created_at": "2023-08-07T06:05:11.000Z", "author_id": "76302546", "context_annotations": [{"domain": {"id": "131", "name": "Unified Twitter Taxonomy", "description": "A taxonomy of user interests. "}, "entity": {"id": "854692455005921281", "name": "Science", "description": "Science"}}], "reply_settings": "everyone", "lang": "in", "id": "1688431069400563712", "edit_history_tweet_ids": ["1688431069400563712"]}, {"public_metrics": {"retweet_count": 0, "reply_count": 1, "like_count": 0, "quote_count": 0, "bookmark_count": 0, "impression_count": 27}, "text": "@poccku jogging itu kan yg buat ngusir nyamuk DBD", "possibly_sensitive": false, "conversation_id": "1688185746656722944", "edit_controls": {"edits_remaining": 5, "is_edit_eligible": false, "editable_until": "2023-08-06T15:40:01.000Z"}, "created_at": "2023-08-06T14:40:01.000Z", "author_id": "478293907", "reply_settings": "everyone", "lang": "in", "id": "1688198247016448000", "edit_history_tweet_ids": ["1688198247016448000"], "entities": {"mentions": [{"start": 0, "end": 7, "username": "poccku", "id": "2758601187"}]}, "referenced_tweets": [{"type": "replied_to", "id": "1688197977750614017"}], "in_reply_to_user_id": "2758601187"}, {"public_metrics": {"retweet_count": 0, "reply_count": 0, "like_count": 0, "quote_count": 0, "bookmark_count": 0, "impression_count": 38}, "text": "gigitan nyamuk terbanyak sih ini, untung bukan nyamuk aedes aegypti, dkk kalo nggak udah dbd. Lebih banyak ini gigitannya drpd pas kena dbd pas kecil https://t.co/QyNP0wiecN", "attachments": {"media_keys": ["3_1688191486326972416"]}, "possibly_sensitive": false, "conversation_id": "1688191496942714885", "edit_controls": {"edits_remaining": 5, "is_edit_eligible": true, "editable_until": "2023-08-06T15:13:12.000Z"}, "entities": {"urls": [{"start": 150, "end": 173, "url": "https://t.co/QyNP0wiecN", "expanded_url": "https://twitter.com/nitelight__/status/1688191496942714885/photo/1", "display_url": "pic.twitter.com/QyNP0wiecN", "media_key": "3_1688191486326972416"}]}, "created_at": "2023-08-06T14:13:12.000Z", "author_id": "610082724", "reply_settings": "everyone", "lang": "in", "id": "1688191496942714885", "edit_history_tweet_ids": ["1688191496942714885"]}]